{
  "resourceLogs": [
    {
      "resource": {
        "attributes": [
          {
            "key": "service.name",
            "value": { "stringValue": "api-server" }
          }
        ],
        "droppedAttributesCount": 0,
        "entityRefs": []
      },
      "scopeLogs": [
        {
          "scope": {
            "name": "",
            "version": "",
            "attributes": [],
            "droppedAttributesCount": 0
          },
          "logRecords": [
            {
              "timeUnixNano": 0,
              "observedTimeUnixNano": 0,
              "severityNumber": "SEVERITY_NUMBER_UNSPECIFIED",
              "severityText": "DEBUG",
              "body": { "stringValue": "debug 1" },
              "attributes": [],
              "droppedAttributesCount": 0,
              "flags": 0,
              "traceId": "",
              "spanId": "",
              "eventName": ""
            },
            {
              "timeUnixNano": 0,
              "observedTimeUnixNano": 0,
              "severityNumber": "SEVERITY_NUMBER_UNSPECIFIED",
              "severityText": "DEBUG",
              "body": { "stringValue": "debug 2" },
              "attributes": [],
              "droppedAttributesCount": 0,
              "flags": 0,
              "traceId": "",
              "spanId": "",
              "eventName": ""
            },
            {
              "timeUnixNano": 0,
              "observedTimeUnixNano": 0,
              "severityNumber": "SEVERITY_NUMBER_UNSPECIFIED",
              "severityText": "DEBUG",
              "body": { "stringValue": "debug 3" },
              "attributes": [],
              "droppedAttributesCount": 0,
              "flags": 0,
              "traceId": "",
              "spanId": "",
              "eventName": ""
            }
          ],
          "schemaUrl": ""
        }
      ],
      "schemaUrl": ""
    }
  ]
}
